kmdr/__init__.py
kmdr/_version.py
kmdr/main.py
kmdr/core/__init__.py
kmdr/core/bases.py
kmdr/core/console.py
kmdr/core/constants.py
kmdr/core/context.py
kmdr/core/defaults.py
kmdr/core/error.py
kmdr/core/protocol.py
kmdr/core/registry.py
kmdr/core/session.py
kmdr/core/structure.py
kmdr/core/utils.py
kmdr/module/__init__.py
kmdr/module/authenticator/CookieAuthenticator.py
kmdr/module/authenticator/LoginAuthenticator.py
kmdr/module/authenticator/__init__.py
kmdr/module/authenticator/utils.py
kmdr/module/configurer/BaseUrlUpdator.py
kmdr/module/configurer/ConfigClearer.py
kmdr/module/configurer/ConfigUnsetter.py
kmdr/module/configurer/OptionLister.py
kmdr/module/configurer/OptionSetter.py
kmdr/module/configurer/__init__.py
kmdr/module/configurer/option_validate.py
kmdr/module/downloader/DirectDownloader.py
kmdr/module/downloader/ReferViaDownloader.py
kmdr/module/downloader/__init__.py
kmdr/module/downloader/download_utils.py
kmdr/module/downloader/misc.py
kmdr/module/lister/BookUrlLister.py
kmdr/module/lister/FollowedBookLister.py
kmdr/module/lister/__init__.py
kmdr/module/lister/utils.py
kmdr/module/picker/ArgsFilterPicker.py
kmdr/module/picker/DefaultVolPicker.py
kmdr/module/picker/__init__.py
kmdr/module/picker/utils.py
kmoe_manga_downloader-1.2.8.dist-info/licenses/LICENSE
kmoe_manga_downloader-1.2.8.dist-info/METADATA
kmoe_manga_downloader-1.2.8.dist-info/WHEEL
kmoe_manga_downloader-1.2.8.dist-info/entry_points.txt
kmoe_manga_downloader-1.2.8.dist-info/top_level.txt
kmoe_manga_downloader-1.2.8.dist-info/RECORD
