Metadata-Version: 2.4
Name: kmoe-manga-downloader
Version: 1.2.8
Summary: A CLI-downloader for site @kox.moe.
Author-email: Chris Zheng <chrisis58@outlook.com>
License: MIT License
Project-URL: Homepage, https://github.com/chrisis58/kmoe-manga-downloader
Project-URL: Issues, https://github.com/chrisis58/kmoe-manga-downloader/issues
Keywords: manga,downloader,kmoe
Classifier: Development Status :: 4 - Beta
Classifier: Programming Language :: Python :: 3
Classifier: License :: OSI Approved :: MIT License
Classifier: Operating System :: OS Independent
Requires-Python: >=3.9
License-File: LICENSE
Requires-Dist: beautifulsoup4~=4.13.4
Requires-Dist: aiohttp~=3.12.15
Requires-Dist: aiofiles~=24.1.0
Requires-Dist: async-lru~=2.0.5
Requires-Dist: rich~=13.9.4
Requires-Dist: yarl~=1.20.1
Requires-Dist: typing-extensions~=4.15.0
Dynamic: license-file
